nanoproof/__init__.py
nanoproof-0.1.0.dist-info/METADATA
nanoproof-0.1.0.dist-info/WHEEL
nanoproof-0.1.0.dist-info/top_level.txt
nanoproof-0.1.0.dist-info/RECORD
