Metadata-Version: 2.4
Name: nanoproof
Version: 0.1.0
Summary: Minimal open-source implementation of AlphaProof
Requires-Python: >=3.9
